{"3636000312":[{"campusName":"主校区","campusAddress":"江西省上饶市信州区志敏大道397号","province":"江西","city":"上饶","district":"信州区","lat":28.421177,"lng":117.97686,"undergraduateScope":"unknown","freshmanOnly":"unknown","nearestMetroStation":"","sourceTitle":"Naptie cn-university-geocoder + DaoSword China-Education-Data + ZsTs119/pg7go Baidu POI 数据集","sourceUrl":"https://github.com/Naptie/cn-university-geocoder","sourceDate":"2026-04-21","confidence":"high","notes":"百度 POI 精确匹配，坐标偏差约 1.17 km。"}],"3636000519":[{"campusName":"主校区","campusAddress":"江西省抚州市王安石大道99号","province":"江西","city":"抚州","district":"临川区","lat":27.951771,"lng":116.407348,"undergraduateScope":"unknown","freshmanOnly":"unknown","nearestMetroStation":"","sourceTitle":"Naptie cn-university-geocoder + DaoSword China-Education-Data + ZsTs119/pg7go Baidu POI 数据集","sourceUrl":"https://github.com/Naptie/cn-university-geocoder","sourceDate":"2026-04-21","confidence":"high","notes":"百度 POI 精确匹配，坐标偏差约 1.18 km。"}],"4136010403":[{"campusName":"东湖校区","campusAddress":"南昌市东湖区八一大道461号","province":"江西","city":"南昌","district":"东湖区","lat":28.683804,"lng":115.906703,"undergraduateScope":"unknown","freshmanOnly":"unknown","nearestMetroStation":"","sourceTitle":"Naptie cn-university-geocoder + DaoSword China-Education-Data + ZsTs119/pg7go Baidu POI 数据集","sourceUrl":"https://github.com/Naptie/cn-university-geocoder","sourceDate":"2026-04-21","confidence":"high","notes":"百度 POI 近似匹配，坐标偏差约 0.93 km。"},{"campusName":"前湖校区","campusAddress":"南昌市红谷滩新区学府大道999号","province":"江西","city":"南昌","district":"新建区","lat":28.656314,"lng":115.801314,"undergraduateScope":"unknown","freshmanOnly":"unknown","nearestMetroStation":"","sourceTitle":"Naptie cn-university-geocoder + DaoSword China-Education-Data + ZsTs119/pg7go Baidu POI 数据集","sourceUrl":"https://github.com/Naptie/cn-university-geocoder","sourceDate":"2026-04-21","confidence":"high","notes":"百度 POI 近似匹配，坐标偏差约 0.94 km。"}],"4136010404":[{"campusName":"主校区","campusAddress":"江西省南昌市经济技术开发区双港东大街808号","province":"江西","city":"南昌","district":"青山湖区","lat":28.747314,"lng":115.864888,"undergraduateScope":"unknown","freshmanOnly":"unknown","nearestMetroStation":"","sourceTitle":"Naptie cn-university-geocoder + DaoSword China-Education-Data + ZsTs119/pg7go Baidu POI 数据集","sourceUrl":"https://github.com/Naptie/cn-university-geocoder","sourceDate":"2026-04-21","confidence":"high","notes":"百度 POI 精确匹配，坐标偏差约 1.15 km。"}],"4136010405":[{"campusName":"抚州校区","campusAddress":"江西省抚州市临川区学府路56号","province":"江西","city":"抚州","district":"临川区","lat":27.98829529143844,"lng":116.35153681690865,"undergraduateScope":"unknown","freshmanOnly":"unknown","nearestMetroStation":"","sourceTitle":"Naptie cn-university-geocoder + DaoSword China-Education-Data + ZsTs119/pg7go Baidu POI 数据集","sourceUrl":"https://github.com/Naptie/cn-university-geocoder","sourceDate":"2026-04-21","confidence":"high","notes":"百度 POI 近似匹配，坐标偏差约 1.12 km。"}],"4136010406":[{"campusName":"主校区","campusAddress":"江西省南昌市丰和南大道696号南昌航空大学招生办公室","province":"江西","city":"南昌","district":"","lat":28.654266,"lng":115.8236,"undergraduateScope":"unknown","freshmanOnly":"unknown","nearestMetroStation":"","sourceTitle":"Naptie cn-university-geocoder + DaoSword China-Education-Data","sourceUrl":"https://github.com/Naptie/cn-university-geocoder","sourceDate":"2026-04-21","confidence":"medium","notes":"辅源：https://github.com/jtchen2k/hcu、https://daxue.cgsop.com/ 可用于后续人工校验校区沿革与本科去向。"}],"4136010407":[{"campusName":"红旗校区","campusAddress":"江西省赣州市红旗大道86号","province":"江西","city":"赣州","district":"章贡区","lat":25.854107617466244,"lng":114.93032670795237,"undergraduateScope":"unknown","freshmanOnly":"unknown","nearestMetroStation":"","sourceTitle":"Naptie cn-university-geocoder + DaoSword China-Education-Data + ZsTs119/pg7go Baidu POI 数据集","sourceUrl":"https://github.com/Naptie/cn-university-geocoder","sourceDate":"2026-04-21","confidence":"high","notes":"校区地址与 DaoSword 宽表中的标注校区名一致。 百度 POI 近似匹配，坐标偏差约 0.91 km。"},{"campusName":"黄金校区","campusAddress":"江西省赣州市客家大道156号","province":"江西","city":"赣州","district":"章贡区","lat":25.843912,"lng":114.924396,"undergraduateScope":"unknown","freshmanOnly":"unknown","nearestMetroStation":"","sourceTitle":"DaoSword China-Education-Data + ZsTs119/pg7go Baidu POI 数据集","sourceUrl":"https://github.com/DaoSword/China-Education-Data","sourceDate":"2026-04-21","confidence":"low","notes":"此校区由 DaoSword 宽表中的标注校址补入；未在 geocoder 主结果中出现，建议后续以学校校区介绍页复核。"},{"campusName":"三江校区","campusAddress":"江西省赣州市客家大道1958号","province":"江西","city":"赣州","district":"","undergraduateScope":"unknown","freshmanOnly":"unknown","nearestMetroStation":"","sourceTitle":"DaoSword China-Education-Data","sourceUrl":"https://github.com/DaoSword/China-Education-Data","sourceDate":"2026-04-21","confidence":"low","notes":"此校区由 DaoSword 宽表中的标注校址补入；未在 geocoder 主结果中出现，建议后续以学校校区介绍页复核。"}],"4136010408":[{"campusName":"主校区","campusAddress":"江西省景德镇市湘湖","province":"江西","city":"景德镇","district":"","lat":29.331472,"lng":117.31142,"undergraduateScope":"unknown","freshmanOnly":"unknown","nearestMetroStation":"","sourceTitle":"Naptie cn-university-geocoder + DaoSword China-Education-Data","sourceUrl":"https://github.com/Naptie/cn-university-geocoder","sourceDate":"2026-04-21","confidence":"medium","notes":"辅源：https://github.com/jtchen2k/hcu、https://daxue.cgsop.com/ 可用于后续人工校验校区沿革与本科去向。"}],"4136010410":[{"campusName":"主校区","campusAddress":"江西省南昌经济技术开发区志敏大道1101号","province":"江西","city":"南昌","district":"青山湖区","lat":28.759484,"lng":115.834361,"undergraduateScope":"unknown","freshmanOnly":"unknown","nearestMetroStation":"","sourceTitle":"Naptie cn-university-geocoder + DaoSword China-Education-Data + ZsTs119/pg7go Baidu POI 数据集","sourceUrl":"https://github.com/Naptie/cn-university-geocoder","sourceDate":"2026-04-21","confidence":"high","notes":"百度 POI 精确匹配，坐标偏差约 1.09 km。"}],"4136010412":[{"campusName":"主校区","campusAddress":"江西省南昌市新建区梅岭大道1688号","province":"江西","city":"南昌","district":"湾里区","lat":28.680645,"lng":115.743958,"undergraduateScope":"unknown","freshmanOnly":"unknown","nearestMetroStation":"","sourceTitle":"Naptie cn-university-geocoder + DaoSword China-Education-Data + ZsTs119/pg7go Baidu POI 数据集","sourceUrl":"https://github.com/Naptie/cn-university-geocoder","sourceDate":"2026-04-21","confidence":"high","notes":"百度 POI 精确匹配，坐标偏差约 1.55 km。"}],"4136010413":[{"campusName":"黄金校区","campusAddress":"江西省赣州蓉江新区和谐大道1号","province":"江西","city":"赣州","district":"赣州蓉江新区","undergraduateScope":"unknown","freshmanOnly":"unknown","nearestMetroStation":"","sourceTitle":"DaoSword China-Education-Data","sourceUrl":"https://github.com/DaoSword/China-Education-Data","sourceDate":"2026-04-21","confidence":"low","notes":"当前仅有聚合校址，尚未接入官方招生章程或校区说明页，暂不参与硬筛选推导。"},{"campusName":"章贡校区","campusAddress":"江西省赣州市章贡区医学院路1号","province":"江西","city":"赣州","district":"赣州市章贡区","undergraduateScope":"unknown","freshmanOnly":"unknown","nearestMetroStation":"","sourceTitle":"DaoSword China-Education-Data","sourceUrl":"https://github.com/DaoSword/China-Education-Data","sourceDate":"2026-04-21","confidence":"low","notes":"当前仅有聚合校址，尚未接入官方招生章程或校区说明页，暂不参与硬筛选推导。"}],"4136010414":[{"campusName":"青山湖校区","campusAddress":"江西省南昌市北京西路437号","province":"江西","city":"南昌","district":"东湖区","lat":28.676521,"lng":115.923606,"undergraduateScope":"unknown","freshmanOnly":"unknown","nearestMetroStation":"","sourceTitle":"Naptie cn-university-geocoder + DaoSword China-Education-Data + ZsTs119/pg7go Baidu POI 数据集","sourceUrl":"https://github.com/Naptie/cn-university-geocoder","sourceDate":"2026-04-21","confidence":"high","notes":"校区地址与 DaoSword 宽表中的标注校区名一致。 百度 POI 近似匹配，坐标偏差约 0.99 km。"},{"campusName":"瑶湖校区","campusAddress":"江西省南昌市紫阳大道99号","province":"江西","city":"南昌","district":"南昌县","lat":28.680545127069,"lng":116.03201583068848,"undergraduateScope":"unknown","freshmanOnly":"unknown","nearestMetroStation":"","sourceTitle":"Naptie cn-university-geocoder + DaoSword China-Education-Data + ZsTs119/pg7go Baidu POI 数据集","sourceUrl":"https://github.com/Naptie/cn-university-geocoder","sourceDate":"2026-04-21","confidence":"high","notes":"校区地址与 DaoSword 宽表中的标注校区名一致。 百度 POI 近似匹配，坐标偏差约 0.85 km。"}],"4136010416":[{"campusName":"主校区","campusAddress":"江西省上饶市信州区志敏大道401号","province":"江西","city":"上饶","district":"信州区","lat":28.420091,"lng":117.96547,"undergraduateScope":"unknown","freshmanOnly":"unknown","nearestMetroStation":"","sourceTitle":"Naptie cn-university-geocoder + DaoSword China-Education-Data + ZsTs119/pg7go Baidu POI 数据集","sourceUrl":"https://github.com/Naptie/cn-university-geocoder","sourceDate":"2026-04-21","confidence":"high","notes":"百度 POI 精确匹配，坐标偏差约 1.17 km。"}],"4136010417":[{"campusName":"北校区","campusAddress":"江西省宜春市宜春北路128号","province":"江西","city":"宜春","district":"","lat":27.804293,"lng":114.383035,"undergraduateScope":"unknown","freshmanOnly":"unknown","nearestMetroStation":"","sourceTitle":"Naptie cn-university-geocoder + DaoSword China-Education-Data","sourceUrl":"https://github.com/Naptie/cn-university-geocoder","sourceDate":"2026-04-21","confidence":"high","notes":"校区地址与 DaoSword 宽表中的标注校区名一致。"},{"campusName":"校本部","campusAddress":"江西省宜春市学府路576号","province":"江西","city":"宜春","district":"","lat":27.790115,"lng":114.356812,"undergraduateScope":"unknown","freshmanOnly":"unknown","nearestMetroStation":"","sourceTitle":"Naptie cn-university-geocoder + DaoSword China-Education-Data","sourceUrl":"https://github.com/Naptie/cn-university-geocoder","sourceDate":"2026-04-21","confidence":"high","notes":"校区地址与 DaoSword 宽表中的标注校区名一致。"}],"4136010418":[{"campusName":"黄金校区","campusAddress":"江西省赣州市蓉江新区师院南路","province":"江西","city":"赣州","district":"章贡区","lat":25.795961,"lng":114.88667,"undergraduateScope":"unknown","freshmanOnly":"unknown","nearestMetroStation":"","sourceTitle":"Naptie cn-university-geocoder + DaoSword China-Education-Data + ZsTs119/pg7go Baidu POI 数据集","sourceUrl":"https://github.com/Naptie/cn-university-geocoder","sourceDate":"2026-04-21","confidence":"high","notes":"百度 POI 近似匹配，坐标偏差约 0.91 km。"},{"campusName":"主校区","campusAddress":"江西省赣州市赣州开发区师院南路","province":"江西","city":"赣州","district":"赣州市赣州开发区","lat":25.854139,"lng":114.926938,"undergraduateScope":"unknown","freshmanOnly":"unknown","nearestMetroStation":"","sourceTitle":"Naptie cn-university-geocoder + DaoSword China-Education-Data","sourceUrl":"https://github.com/Naptie/cn-university-geocoder","sourceDate":"2026-04-21","confidence":"medium","notes":"辅源：https://github.com/jtchen2k/hcu、https://daxue.cgsop.com/ 可用于后续人工校验校区沿革与本科去向。"}],"4136010419":[{"campusName":"主校区","campusAddress":"江西省吉安市青原区学苑路28号","province":"江西","city":"吉安","district":"青原区","lat":27.11529,"lng":115.027201,"undergraduateScope":"unknown","freshmanOnly":"unknown","nearestMetroStation":"","sourceTitle":"Naptie cn-university-geocoder + DaoSword China-Education-Data + ZsTs119/pg7go Baidu POI 数据集","sourceUrl":"https://github.com/Naptie/cn-university-geocoder","sourceDate":"2026-04-21","confidence":"high","notes":"百度 POI 精确匹配，坐标偏差约 1.19 km。"}],"4136010421":[{"campusName":"蛟桥园校区","campusAddress":"江西省南昌市国家经济技术开发区双港东大街169号","province":"江西","city":"南昌","district":"青山湖区","lat":28.75849,"lng":115.88687,"undergraduateScope":"unknown","freshmanOnly":"unknown","nearestMetroStation":"","sourceTitle":"Naptie cn-university-geocoder + DaoSword China-Education-Data + ZsTs119/pg7go Baidu POI 数据集","sourceUrl":"https://github.com/Naptie/cn-university-geocoder","sourceDate":"2026-04-21","confidence":"high","notes":"校区地址与 DaoSword 宽表中的标注校区名一致。 百度 POI 近似匹配，坐标偏差约 2.87 km。"},{"campusName":"麦庐园校区","campusAddress":"江西省南昌市国家经济技术开发区玉屏大道","province":"江西","city":"南昌","district":"国家经济技术开发区","lat":28.784688,"lng":115.861876,"undergraduateScope":"unknown","freshmanOnly":"unknown","nearestMetroStation":"","sourceTitle":"Naptie cn-university-geocoder + DaoSword China-Education-Data","sourceUrl":"https://github.com/Naptie/cn-university-geocoder","sourceDate":"2026-04-21","confidence":"high","notes":"校区地址与 DaoSword 宽表中的标注校区名一致。"}],"4136010839":[{"campusName":"青山湖校区","campusAddress":"江西省南昌市青山湖北大道1988号","province":"江西","city":"南昌","district":"","lat":28.682004,"lng":115.947485,"undergraduateScope":"unknown","freshmanOnly":"unknown","nearestMetroStation":"","sourceTitle":"Naptie cn-university-geocoder + DaoSword China-Education-Data","sourceUrl":"https://github.com/Naptie/cn-university-geocoder","sourceDate":"2026-04-21","confidence":"high","notes":"校区地址与 DaoSword 宽表中的标注校区名一致。"},{"campusName":"瑶湖校区","campusAddress":"江西省南昌市高新区天祥大道388号","province":"江西","city":"南昌","district":"南昌市高新区","lat":28.693926,"lng":116.024447,"undergraduateScope":"unknown","freshmanOnly":"unknown","nearestMetroStation":"","sourceTitle":"Naptie cn-university-geocoder + DaoSword China-Education-Data","sourceUrl":"https://github.com/Naptie/cn-university-geocoder","sourceDate":"2026-04-21","confidence":"high","notes":"校区地址与 DaoSword 宽表中的标注校区名一致。"}],"4136010846":[{"campusName":"主校区","campusAddress":"江西省南昌市瑶湖高校园区紫阳大道115号","province":"江西","city":"南昌","district":"南昌市瑶湖高校园区","lat":28.683696,"lng":116.01434,"undergraduateScope":"unknown","freshmanOnly":"unknown","nearestMetroStation":"","sourceTitle":"Naptie cn-university-geocoder + DaoSword China-Education-Data","sourceUrl":"https://github.com/Naptie/cn-university-geocoder","sourceDate":"2026-04-21","confidence":"medium","notes":"辅源：https://github.com/jtchen2k/hcu、https://daxue.cgsop.com/ 可用于后续人工校验校区沿革与本科去向。"}],"4136010888":[{"campusName":"主校区","campusAddress":"江西省上饶市信州区志敏大道399号","province":"江西","city":"上饶","district":"信州区","lat":28.421663,"lng":117.971806,"undergraduateScope":"unknown","freshmanOnly":"unknown","nearestMetroStation":"","sourceTitle":"Naptie cn-university-geocoder + DaoSword China-Education-Data + ZsTs119/pg7go Baidu POI 数据集","sourceUrl":"https://github.com/Naptie/cn-university-geocoder","sourceDate":"2026-04-21","confidence":"high","notes":"百度 POI 精确匹配，坐标偏差约 1.17 km。"}],"4136010894":[{"campusName":"主校区","campusAddress":"江西省景德镇市浮梁县浮梁大道3号","province":"江西","city":"景德镇","district":"景德镇市浮梁县","lat":29.379877,"lng":117.238492,"undergraduateScope":"unknown","freshmanOnly":"unknown","nearestMetroStation":"","sourceTitle":"Naptie cn-university-geocoder + DaoSword China-Education-Data","sourceUrl":"https://github.com/Naptie/cn-university-geocoder","sourceDate":"2026-04-21","confidence":"medium","notes":"辅源：https://github.com/jtchen2k/hcu、https://daxue.cgsop.com/ 可用于后续人工校验校区沿革与本科去向。"}],"4136010895":[{"campusName":"主校区","campusAddress":"江西省萍乡市萍安北大道211号","province":"江西","city":"萍乡","district":"安源区","lat":27.629803,"lng":113.874646,"undergraduateScope":"unknown","freshmanOnly":"unknown","nearestMetroStation":"","sourceTitle":"Naptie cn-university-geocoder + DaoSword China-Education-Data + ZsTs119/pg7go Baidu POI 数据集","sourceUrl":"https://github.com/Naptie/cn-university-geocoder","sourceDate":"2026-04-21","confidence":"high","notes":"百度 POI 精确匹配，坐标偏差约 1.36 km。"}],"4136011318":[{"campusName":"枫林校区","campusAddress":"江西省南昌市昌北经济开发区枫林大道605号","province":"江西","city":"南昌","district":"昌北经济开发区","lat":28.736236,"lng":115.840901,"undergraduateScope":"unknown","freshmanOnly":"unknown","nearestMetroStation":"","sourceTitle":"Naptie cn-university-geocoder + DaoSword China-Education-Data","sourceUrl":"https://github.com/Naptie/cn-university-geocoder","sourceDate":"2026-04-21","confidence":"high","notes":"校区地址与 DaoSword 宽表中的标注校区名一致。"},{"campusName":"红角洲校区","campusAddress":"江西省南昌市红角洲学府大道589号","province":"江西","city":"南昌","district":"新建区","lat":28.667065,"lng":115.819535,"undergraduateScope":"unknown","freshmanOnly":"unknown","nearestMetroStation":"","sourceTitle":"Naptie cn-university-geocoder + DaoSword China-Education-Data + ZsTs119/pg7go Baidu POI 数据集","sourceUrl":"https://github.com/Naptie/cn-university-geocoder","sourceDate":"2026-04-21","confidence":"high","notes":"校区地址与 DaoSword 宽表中的标注校区名一致。 百度 POI 近似匹配，坐标偏差约 0.93 km。"}],"4136011319":[{"campusName":"彭家桥校区","campusAddress":"江西省南昌市青山湖区北京东路59号","province":"江西","city":"南昌","district":"南昌市青山湖区","undergraduateScope":"unknown","freshmanOnly":"unknown","nearestMetroStation":"","sourceTitle":"DaoSword China-Education-Data","sourceUrl":"https://github.com/DaoSword/China-Education-Data","sourceDate":"2026-04-21","confidence":"low","notes":"当前仅有聚合校址，尚未接入官方招生章程或校区说明页，暂不参与硬筛选推导。"},{"campusName":"瑶湖校区","campusAddress":"江西省南昌市高新技术开发区天祥大道289号","province":"江西","city":"南昌","district":"高新技术开发区","undergraduateScope":"unknown","freshmanOnly":"unknown","nearestMetroStation":"","sourceTitle":"DaoSword China-Education-Data","sourceUrl":"https://github.com/DaoSword/China-Education-Data","sourceDate":"2026-04-21","confidence":"low","notes":"当前仅有聚合校址，尚未接入官方招生章程或校区说明页，暂不参与硬筛选推导。"}],"4136011504":[{"campusName":"主校区","campusAddress":"江西省南昌市新建区梅岭大道1666号","province":"江西","city":"南昌","district":"新建区","lat":28.667959,"lng":115.749896,"undergraduateScope":"unknown","freshmanOnly":"unknown","nearestMetroStation":"","sourceTitle":"Naptie cn-university-geocoder + DaoSword China-Education-Data + ZsTs119/pg7go Baidu POI 数据集","sourceUrl":"https://github.com/Naptie/cn-university-geocoder","sourceDate":"2026-04-21","confidence":"high","notes":"百度 POI 精确匹配，坐标偏差约 1.17 km。"}],"4136011505":[{"campusName":"鹤问湖校区","campusAddress":"江西省九江市九瑞大道91号","province":"江西","city":"九江","district":"浔阳区","lat":29.699997,"lng":115.960508,"undergraduateScope":"unknown","freshmanOnly":"unknown","nearestMetroStation":"","sourceTitle":"Naptie cn-university-geocoder + DaoSword China-Education-Data + ZsTs119/pg7go Baidu POI 数据集","sourceUrl":"https://github.com/Naptie/cn-university-geocoder","sourceDate":"2026-04-21","confidence":"high","notes":"校区地址与 DaoSword 宽表中的标注校区名一致。 百度 POI 近似匹配，坐标偏差约 1.15 km。"},{"campusName":"濂溪校区","campusAddress":"江西省九江市濂溪大道88号","province":"江西","city":"九江","district":"濂溪区","lat":29.655987,"lng":116.00084,"undergraduateScope":"unknown","freshmanOnly":"unknown","nearestMetroStation":"","sourceTitle":"Naptie cn-university-geocoder + DaoSword China-Education-Data + ZsTs119/pg7go Baidu POI 数据集","sourceUrl":"https://github.com/Naptie/cn-university-geocoder","sourceDate":"2026-04-21","confidence":"high","notes":"校区地址与 DaoSword 宽表中的标注校区名一致。 百度 POI 近似匹配，坐标偏差约 0.83 km。"}],"4136011508":[{"campusName":"主校区","campusAddress":"江西省新余市高新区阳光大道2666号","province":"江西","city":"新余","district":"渝水区","lat":27.858529,"lng":114.995442,"undergraduateScope":"unknown","freshmanOnly":"unknown","nearestMetroStation":"","sourceTitle":"Naptie cn-university-geocoder + DaoSword China-Education-Data + ZsTs119/pg7go Baidu POI 数据集","sourceUrl":"https://github.com/Naptie/cn-university-geocoder","sourceDate":"2026-04-21","confidence":"high","notes":"百度 POI 精确匹配，坐标偏差约 0.89 km。"}],"4136011785":[{"campusName":"濂溪校区","campusAddress":"江西省九江市濂溪区前进东路881号","province":"江西","city":"九江","district":"九江市濂溪区","undergraduateScope":"unknown","freshmanOnly":"unknown","nearestMetroStation":"","sourceTitle":"DaoSword China-Education-Data","sourceUrl":"https://github.com/DaoSword/China-Education-Data","sourceDate":"2026-04-21","confidence":"low","notes":"当前仅有聚合校址，尚未接入官方招生章程或校区说明页，暂不参与硬筛选推导。"},{"campusName":"十里校区","campusAddress":"江西省九江市濂溪区十里大道1188号","province":"江西","city":"九江","district":"九江市濂溪区","undergraduateScope":"unknown","freshmanOnly":"unknown","nearestMetroStation":"","sourceTitle":"DaoSword China-Education-Data","sourceUrl":"https://github.com/DaoSword/China-Education-Data","sourceDate":"2026-04-21","confidence":"low","notes":"当前仅有聚合校址，尚未接入官方招生章程或校区说明页，暂不参与硬筛选推导。"}],"4136011843":[{"campusName":"主校区","campusAddress":"江西省九江市前进东路551号","province":"江西","city":"九江","district":"","lat":29.713505,"lng":115.991082,"undergraduateScope":"unknown","freshmanOnly":"unknown","nearestMetroStation":"","sourceTitle":"Naptie cn-university-geocoder + DaoSword China-Education-Data","sourceUrl":"https://github.com/Naptie/cn-university-geocoder","sourceDate":"2026-04-21","confidence":"medium","notes":"辅源：https://github.com/jtchen2k/hcu、https://daxue.cgsop.com/ 可用于后续人工校验校区沿革与本科去向。"}],"4136012766":[{"campusName":"主校区","campusAddress":"江西省新余市天工南大道1688号","province":"江西","city":"新余","district":"","lat":27.779393,"lng":114.839244,"undergraduateScope":"unknown","freshmanOnly":"unknown","nearestMetroStation":"","sourceTitle":"Naptie cn-university-geocoder + DaoSword China-Education-Data","sourceUrl":"https://github.com/Naptie/cn-university-geocoder","sourceDate":"2026-04-21","confidence":"medium","notes":"辅源：https://github.com/jtchen2k/hcu、https://daxue.cgsop.com/ 可用于后续人工校验校区沿革与本科去向。"}],"4136012795":[{"campusName":"英雄主校区","campusAddress":"南昌市青山湖区经济技术开发区英雄大道901号","province":"江西","city":"南昌","district":"青山湖区","lat":28.783236365942244,"lng":115.8613866448975,"undergraduateScope":"unknown","freshmanOnly":"unknown","nearestMetroStation":"","sourceTitle":"Naptie cn-university-geocoder + DaoSword China-Education-Data + ZsTs119/pg7go Baidu POI 数据集","sourceUrl":"https://github.com/Naptie/cn-university-geocoder","sourceDate":"2026-04-21","confidence":"high","notes":"百度 POI 近似匹配，坐标偏差约 0.81 km。"}],"4136012929":[{"campusName":"主校区","campusAddress":"江西省南昌市昌北开发区长青路76号","province":"江西","city":"南昌","district":"南昌市昌北开发区","lat":28.712163,"lng":115.839032,"undergraduateScope":"unknown","freshmanOnly":"unknown","nearestMetroStation":"","sourceTitle":"Naptie cn-university-geocoder + DaoSword China-Education-Data","sourceUrl":"https://github.com/Naptie/cn-university-geocoder","sourceDate":"2026-04-21","confidence":"medium","notes":"辅源：https://github.com/jtchen2k/hcu、https://daxue.cgsop.com/ 可用于后续人工校验校区沿革与本科去向。"}],"4136012930":[{"campusName":"主校区","campusAddress":"江西省景德镇市浮梁县工美大道666号","province":"江西","city":"景德镇","district":"景德镇市浮梁县","lat":29.380456,"lng":117.206379,"undergraduateScope":"unknown","freshmanOnly":"unknown","nearestMetroStation":"","sourceTitle":"Naptie cn-university-geocoder + DaoSword China-Education-Data","sourceUrl":"https://github.com/Naptie/cn-university-geocoder","sourceDate":"2026-04-21","confidence":"medium","notes":"辅源：https://github.com/jtchen2k/hcu、https://daxue.cgsop.com/ 可用于后续人工校验校区沿革与本科去向。"}],"4136012932":[{"campusName":"主校区","campusAddress":"江西省南昌市经济技术开发区丁香路1号","province":"江西","city":"南昌","district":"湾里区","lat":28.708919,"lng":115.783574,"undergraduateScope":"unknown","freshmanOnly":"unknown","nearestMetroStation":"","sourceTitle":"Naptie cn-university-geocoder + DaoSword China-Education-Data + ZsTs119/pg7go Baidu POI 数据集","sourceUrl":"https://github.com/Naptie/cn-university-geocoder","sourceDate":"2026-04-21","confidence":"high","notes":"百度 POI 精确匹配，坐标偏差约 1.14 km。"}],"4136012933":[{"campusName":"主校区","campusAddress":"江西省南昌市昌北经济开发区海棠南路268号","province":"江西","city":"南昌","district":"昌北经济开发区","lat":28.720782,"lng":115.803723,"undergraduateScope":"unknown","freshmanOnly":"unknown","nearestMetroStation":"","sourceTitle":"Naptie cn-university-geocoder + DaoSword China-Education-Data","sourceUrl":"https://github.com/Naptie/cn-university-geocoder","sourceDate":"2026-04-21","confidence":"medium","notes":"辅源：https://github.com/jtchen2k/hcu、https://daxue.cgsop.com/ 可用于后续人工校验校区沿革与本科去向。"}],"4136012934":[{"campusName":"主校区","campusAddress":"江西省赣州市湖边经济技术开发区（宝葫芦农庄斜对面）","province":"江西","city":"赣州","district":"章贡区","lat":25.887139,"lng":114.90988,"undergraduateScope":"unknown","freshmanOnly":"unknown","nearestMetroStation":"","sourceTitle":"Naptie cn-university-geocoder + DaoSword China-Education-Data + ZsTs119/pg7go Baidu POI 数据集","sourceUrl":"https://github.com/Naptie/cn-university-geocoder","sourceDate":"2026-04-21","confidence":"high","notes":"百度 POI 精确匹配，坐标偏差约 1.16 km。"}],"4136012936":[{"campusName":"主校区","campusAddress":"江西省南昌市庐山中大道1201号","province":"江西","city":"南昌","district":"","lat":28.759422,"lng":115.854108,"undergraduateScope":"unknown","freshmanOnly":"unknown","nearestMetroStation":"","sourceTitle":"Naptie cn-university-geocoder + DaoSword China-Education-Data","sourceUrl":"https://github.com/Naptie/cn-university-geocoder","sourceDate":"2026-04-21","confidence":"medium","notes":"辅源：https://github.com/jtchen2k/hcu、https://daxue.cgsop.com/ 可用于后续人工校验校区沿革与本科去向。"}],"4136012937":[{"campusName":"主校区","campusAddress":"江西省鹰潭市信江新区滨江东路2号","province":"江西","city":"鹰潭","district":"鹰潭市信江新区","lat":28.230404,"lng":117.041424,"undergraduateScope":"unknown","freshmanOnly":"unknown","nearestMetroStation":"","sourceTitle":"Naptie cn-university-geocoder + DaoSword China-Education-Data","sourceUrl":"https://github.com/Naptie/cn-university-geocoder","sourceDate":"2026-04-21","confidence":"medium","notes":"辅源：https://github.com/jtchen2k/hcu、https://daxue.cgsop.com/ 可用于后续人工校验校区沿革与本科去向。"}],"4136012938":[{"campusName":"主校区","campusAddress":"江西省南昌市新建区宏福大道2888号","province":"江西","city":"南昌","district":"新建区","lat":28.668004,"lng":115.698057,"undergraduateScope":"unknown","freshmanOnly":"unknown","nearestMetroStation":"","sourceTitle":"Naptie cn-university-geocoder + DaoSword China-Education-Data + ZsTs119/pg7go Baidu POI 数据集","sourceUrl":"https://github.com/Naptie/cn-university-geocoder","sourceDate":"2026-04-21","confidence":"high","notes":"百度 POI 精确匹配，坐标偏差约 1.21 km。"}],"4136012939":[{"campusName":"主校区","campusAddress":"江西省南昌市青云谱区气象路58号","province":"江西","city":"南昌","district":"青云谱区","lat":28.590743,"lng":115.900953,"undergraduateScope":"unknown","freshmanOnly":"unknown","nearestMetroStation":"","sourceTitle":"Naptie cn-university-geocoder + DaoSword China-Education-Data + ZsTs119/pg7go Baidu POI 数据集","sourceUrl":"https://github.com/Naptie/cn-university-geocoder","sourceDate":"2026-04-21","confidence":"high","notes":"百度 POI 精确匹配，坐标偏差约 1.15 km。"}],"4136012940":[{"campusName":"主校区","campusAddress":"江西省南昌市经济技术开发区双港东大街644支路395号","province":"江西","city":"南昌","district":"青山湖区","lat":28.738698,"lng":115.854877,"undergraduateScope":"unknown","freshmanOnly":"unknown","nearestMetroStation":"","sourceTitle":"Naptie cn-university-geocoder + DaoSword China-Education-Data + ZsTs119/pg7go Baidu POI 数据集","sourceUrl":"https://github.com/Naptie/cn-university-geocoder","sourceDate":"2026-04-21","confidence":"high","notes":"百度 POI 精确匹配，坐标偏差约 1.15 km。"}],"4136012941":[{"campusName":"主校区","campusAddress":"江西省九江市青年路96号","province":"江西","city":"九江","district":"浔阳区","lat":29.707597,"lng":115.989786,"undergraduateScope":"unknown","freshmanOnly":"unknown","nearestMetroStation":"","sourceTitle":"Naptie cn-university-geocoder + DaoSword China-Education-Data + ZsTs119/pg7go Baidu POI 数据集","sourceUrl":"https://github.com/Naptie/cn-university-geocoder","sourceDate":"2026-04-21","confidence":"high","notes":"百度 POI 精确匹配，坐标偏差约 1.18 km。"}],"4136012942":[{"campusName":"主校区","campusAddress":"江西省赣州市经济技术开发区高校园区文峰路9号","province":"江西","city":"赣州","district":"市经济技术开发区","lat":25.80571,"lng":114.888787,"undergraduateScope":"unknown","freshmanOnly":"unknown","nearestMetroStation":"","sourceTitle":"Naptie cn-university-geocoder + DaoSword China-Education-Data","sourceUrl":"https://github.com/Naptie/cn-university-geocoder","sourceDate":"2026-04-21","confidence":"medium","notes":"辅源：https://github.com/jtchen2k/hcu、https://daxue.cgsop.com/ 可用于后续人工校验校区沿革与本科去向。"}],"4136012943":[{"campusName":"主校区","campusAddress":"江西省南昌市紫阳大道338号","province":"江西","city":"南昌","district":"南昌县","lat":28.673739,"lng":115.994288,"undergraduateScope":"unknown","freshmanOnly":"unknown","nearestMetroStation":"","sourceTitle":"Naptie cn-university-geocoder + DaoSword China-Education-Data + ZsTs119/pg7go Baidu POI 数据集","sourceUrl":"https://github.com/Naptie/cn-university-geocoder","sourceDate":"2026-04-21","confidence":"high","notes":"百度 POI 精确匹配，坐标偏差约 1.16 km。"}],"4136012944":[{"campusName":"主校区","campusAddress":"江西省萍乡市经济开发区玉湖东路106号区","province":"江西","city":"萍乡","district":"安源区","lat":27.665586,"lng":113.89687,"undergraduateScope":"unknown","freshmanOnly":"unknown","nearestMetroStation":"","sourceTitle":"Naptie cn-university-geocoder + DaoSword China-Education-Data + ZsTs119/pg7go Baidu POI 数据集","sourceUrl":"https://github.com/Naptie/cn-university-geocoder","sourceDate":"2026-04-21","confidence":"high","notes":"百度 POI 精确匹配，坐标偏差约 1.19 km。"}],"4136012976":[{"campusName":"主校区","campusAddress":"江西省南昌市昌北经济技术开发区枫林大道168号","province":"江西","city":"南昌","district":"昌北经济技术开发区","lat":28.736393,"lng":115.735101,"undergraduateScope":"unknown","freshmanOnly":"unknown","nearestMetroStation":"","sourceTitle":"Naptie cn-university-geocoder + DaoSword China-Education-Data","sourceUrl":"https://github.com/Naptie/cn-university-geocoder","sourceDate":"2026-04-21","confidence":"medium","notes":"辅源：https://github.com/jtchen2k/hcu、https://daxue.cgsop.com/ 可用于后续人工校验校区沿革与本科去向。"}],"4136013418":[{"campusName":"主校区","campusAddress":"江西省南昌市向塘经济开发区丽湖中大道103号","province":"江西","city":"南昌","district":"南昌县","lat":28.457795,"lng":115.946318,"undergraduateScope":"unknown","freshmanOnly":"unknown","nearestMetroStation":"","sourceTitle":"Naptie cn-university-geocoder + DaoSword China-Education-Data + ZsTs119/pg7go Baidu POI 数据集","sourceUrl":"https://github.com/Naptie/cn-university-geocoder","sourceDate":"2026-04-21","confidence":"high","notes":"百度 POI 精确匹配，坐标偏差约 1.15 km。"}],"4136013419":[{"campusName":"主校区","campusAddress":"江西省南昌市银三角316国道金山一号","province":"江西","city":"南昌","district":"南昌县","lat":28.481607,"lng":115.954821,"undergraduateScope":"unknown","freshmanOnly":"unknown","nearestMetroStation":"","sourceTitle":"Naptie cn-university-geocoder + DaoSword China-Education-Data + ZsTs119/pg7go Baidu POI 数据集","sourceUrl":"https://github.com/Naptie/cn-university-geocoder","sourceDate":"2026-04-21","confidence":"high","notes":"百度 POI 精确匹配，坐标偏差约 1.15 km。"}],"4136013420":[{"campusName":"主校区","campusAddress":"江西省南昌市安义凤凰开发区前进东路8号","province":"江西","city":"南昌","district":"安义凤凰开发区","lat":28.548897,"lng":115.939145,"undergraduateScope":"unknown","freshmanOnly":"unknown","nearestMetroStation":"","sourceTitle":"Naptie cn-university-geocoder + DaoSword China-Education-Data","sourceUrl":"https://github.com/Naptie/cn-university-geocoder","sourceDate":"2026-04-21","confidence":"medium","notes":"辅源：https://github.com/jtchen2k/hcu、https://daxue.cgsop.com/ 可用于后续人工校验校区沿革与本科去向。"}],"4136013421":[{"campusName":"主校区","campusAddress":"江西省南昌市红谷滩新区阁皂山大道998号","province":"江西","city":"南昌","district":"南昌市红谷滩新区","lat":28.692629,"lng":116.025964,"undergraduateScope":"unknown","freshmanOnly":"unknown","nearestMetroStation":"","sourceTitle":"Naptie cn-university-geocoder + DaoSword China-Education-Data","sourceUrl":"https://github.com/Naptie/cn-university-geocoder","sourceDate":"2026-04-21","confidence":"medium","notes":"辅源：https://github.com/jtchen2k/hcu、https://daxue.cgsop.com/ 可用于后续人工校验校区沿革与本科去向。"}],"4136013422":[{"campusName":"主校区","campusAddress":"江西省南昌市天祥大道291号","province":"江西","city":"南昌","district":"","lat":28.701429,"lng":116.02629,"undergraduateScope":"unknown","freshmanOnly":"unknown","nearestMetroStation":"","sourceTitle":"Naptie cn-university-geocoder + DaoSword China-Education-Data","sourceUrl":"https://github.com/Naptie/cn-university-geocoder","sourceDate":"2026-04-21","confidence":"medium","notes":"辅源：https://github.com/jtchen2k/hcu、https://daxue.cgsop.com/ 可用于后续人工校验校区沿革与本科去向。"}],"4136013423":[{"campusName":"主校区","campusAddress":"江西省南昌市红角洲高校园区嘉言路699号","province":"江西","city":"南昌","district":"新建区","lat":28.656959,"lng":115.782511,"undergraduateScope":"unknown","freshmanOnly":"unknown","nearestMetroStation":"","sourceTitle":"Naptie cn-university-geocoder + DaoSword China-Education-Data + ZsTs119/pg7go Baidu POI 数据集","sourceUrl":"https://github.com/Naptie/cn-university-geocoder","sourceDate":"2026-04-21","confidence":"high","notes":"百度 POI 精确匹配，坐标偏差约 1.17 km。"}],"4136013424":[{"campusName":"主校区","campusAddress":"江西省宜春市锦绣大道996号","province":"江西","city":"宜春","district":"袁州区","lat":27.8005,"lng":114.362968,"undergraduateScope":"unknown","freshmanOnly":"unknown","nearestMetroStation":"","sourceTitle":"Naptie cn-university-geocoder + DaoSword China-Education-Data + ZsTs119/pg7go Baidu POI 数据集","sourceUrl":"https://github.com/Naptie/cn-university-geocoder","sourceDate":"2026-04-21","confidence":"high","notes":"百度 POI 精确匹配，坐标偏差约 1.21 km。"}],"4136013425":[{"campusName":"主校区","campusAddress":"江西省萍乡市安源区高坑镇周家坊","province":"江西","city":"萍乡","district":"安源区","lat":27.62367,"lng":113.97458,"undergraduateScope":"unknown","freshmanOnly":"unknown","nearestMetroStation":"","sourceTitle":"Naptie cn-university-geocoder + DaoSword China-Education-Data + ZsTs119/pg7go Baidu POI 数据集","sourceUrl":"https://github.com/Naptie/cn-university-geocoder","sourceDate":"2026-04-21","confidence":"high","notes":"百度 POI 精确匹配，坐标偏差约 1.20 km。"}],"4136013426":[{"campusName":"主校区","campusAddress":"江西省南昌市莲塘北大道1636号","province":"江西","city":"南昌","district":"","lat":28.565583,"lng":115.933036,"undergraduateScope":"unknown","freshmanOnly":"unknown","nearestMetroStation":"","sourceTitle":"Naptie cn-university-geocoder + DaoSword China-Education-Data","sourceUrl":"https://github.com/Naptie/cn-university-geocoder","sourceDate":"2026-04-21","confidence":"medium","notes":"辅源：https://github.com/jtchen2k/hcu、https://daxue.cgsop.com/ 可用于后续人工校验校区沿革与本科去向。"}],"4136013427":[{"campusName":"主校区","campusAddress":"江西省南昌市小蓝经济开发区汇仁大道999号","province":"江西","city":"南昌","district":"小蓝经济开发区","lat":28.575547,"lng":115.877325,"undergraduateScope":"unknown","freshmanOnly":"unknown","nearestMetroStation":"","sourceTitle":"Naptie cn-university-geocoder + DaoSword China-Education-Data","sourceUrl":"https://github.com/Naptie/cn-university-geocoder","sourceDate":"2026-04-21","confidence":"medium","notes":"辅源：https://github.com/jtchen2k/hcu、https://daxue.cgsop.com/ 可用于后续人工校验校区沿革与本科去向。"}],"4136013428":[{"campusName":"主校区","campusAddress":"江西省抚州市东临路276号","province":"江西","city":"抚州","district":"","lat":27.957991,"lng":116.389771,"undergraduateScope":"unknown","freshmanOnly":"unknown","nearestMetroStation":"","sourceTitle":"Naptie cn-university-geocoder + DaoSword China-Education-Data","sourceUrl":"https://github.com/Naptie/cn-university-geocoder","sourceDate":"2026-04-21","confidence":"medium","notes":"辅源：https://github.com/jtchen2k/hcu、https://daxue.cgsop.com/ 可用于后续人工校验校区沿革与本科去向。"}],"4136013429":[{"campusName":"共青校区","campusAddress":"江西省九江共青城市五四大道199号","province":"江西","city":"南昌","district":"","lat":29.17335,"lng":115.801317,"undergraduateScope":"unknown","freshmanOnly":"unknown","nearestMetroStation":"","sourceTitle":"Naptie cn-university-geocoder + DaoSword China-Education-Data","sourceUrl":"https://github.com/Naptie/cn-university-geocoder","sourceDate":"2026-04-21","confidence":"high","notes":"校区地址与 DaoSword 宽表中的标注校区名一致。"},{"campusName":"南昌校区","campusAddress":"江西省南昌市北京东路339号","province":"江西","city":"南昌","district":"","lat":28.678174,"lng":115.94358,"undergraduateScope":"unknown","freshmanOnly":"unknown","nearestMetroStation":"","sourceTitle":"Naptie cn-university-geocoder + DaoSword China-Education-Data","sourceUrl":"https://github.com/Naptie/cn-university-geocoder","sourceDate":"2026-04-21","confidence":"high","notes":"校区地址与 DaoSword 宽表中的标注校区名一致。"}],"4136013430":[{"campusName":"主校区","campusAddress":"江西省共青城市南湖大道465号","province":"江西","city":"九江","district":"","lat":29.230721,"lng":115.802184,"undergraduateScope":"unknown","freshmanOnly":"unknown","nearestMetroStation":"","sourceTitle":"Naptie cn-university-geocoder + DaoSword China-Education-Data","sourceUrl":"https://github.com/Naptie/cn-university-geocoder","sourceDate":"2026-04-21","confidence":"medium","notes":"辅源：https://github.com/jtchen2k/hcu、https://daxue.cgsop.com/ 可用于后续人工校验校区沿革与本科去向。"}],"4136013431":[{"campusName":"主校区","campusAddress":"江西省南昌经济技术开发区黄家湖东路111号","province":"江西","city":"南昌","district":"南昌经济技术开发区","lat":28.548897,"lng":115.939145,"undergraduateScope":"unknown","freshmanOnly":"unknown","nearestMetroStation":"","sourceTitle":"Naptie cn-university-geocoder + DaoSword China-Education-Data","sourceUrl":"https://github.com/Naptie/cn-university-geocoder","sourceDate":"2026-04-21","confidence":"medium","notes":"辅源：https://github.com/jtchen2k/hcu、https://daxue.cgsop.com/ 可用于后续人工校验校区沿革与本科去向。"}],"4136013432":[{"campusName":"主校区","campusAddress":"江西省抚州市学府路56号","province":"江西","city":"抚州","district":"","lat":27.991897,"lng":116.346313,"undergraduateScope":"unknown","freshmanOnly":"unknown","nearestMetroStation":"","sourceTitle":"Naptie cn-university-geocoder + DaoSword China-Education-Data","sourceUrl":"https://github.com/Naptie/cn-university-geocoder","sourceDate":"2026-04-21","confidence":"medium","notes":"辅源：https://github.com/jtchen2k/hcu、https://daxue.cgsop.com/ 可用于后续人工校验校区沿革与本科去向。"}],"4136013433":[{"campusName":"主校区","campusAddress":"江西省南昌市赣江新区共青城市青年大道69号","province":"江西","city":"南昌","district":"南昌市赣江新区","lat":28.658821,"lng":115.935452,"undergraduateScope":"unknown","freshmanOnly":"unknown","nearestMetroStation":"","sourceTitle":"DaoSword China-Education-Data + GaoHR 全国大学基本信息","sourceUrl":"https://github.com/DaoSword/China-Education-Data","sourceDate":"2026-04-21","confidence":"medium","notes":"已补 GaoHR 2021 校级坐标；当前为学校级校址占位；需要后续 deep research 继续补本科生具体校区、是否大一分校和地铁距离。"}],"4136013434":[{"campusName":"主校区","campusAddress":"江西省赣州市章贡区客家大道156号","province":"江西","city":"赣州","district":"赣州市章贡区","lat":25.841317,"lng":114.913128,"undergraduateScope":"unknown","freshmanOnly":"unknown","nearestMetroStation":"","sourceTitle":"Naptie cn-university-geocoder + DaoSword China-Education-Data","sourceUrl":"https://github.com/Naptie/cn-university-geocoder","sourceDate":"2026-04-21","confidence":"medium","notes":"辅源：https://github.com/jtchen2k/hcu、https://daxue.cgsop.com/ 可用于后续人工校验校区沿革与本科去向。"}],"4136013435":[{"campusName":"主校区","campusAddress":"江西省景德镇市珠山区和谐大道向东至福佑路与红塔路相交处","province":"江西","city":"景德镇","district":"景德镇市珠山区","lat":29.308442,"lng":117.187694,"undergraduateScope":"unknown","freshmanOnly":"unknown","nearestMetroStation":"","sourceTitle":"Naptie cn-university-geocoder + DaoSword China-Education-Data","sourceUrl":"https://github.com/Naptie/cn-university-geocoder","sourceDate":"2026-04-21","confidence":"medium","notes":"辅源：https://github.com/jtchen2k/hcu、https://daxue.cgsop.com/ 可用于后续人工校验校区沿革与本科去向。"}],"4136013436":[{"campusName":"主校区","campusAddress":"江西省共青城市南湖新城青年大道79号","province":"江西","city":"南昌","district":"","lat":28.679902,"lng":116.024397,"undergraduateScope":"unknown","freshmanOnly":"unknown","nearestMetroStation":"","sourceTitle":"DaoSword China-Education-Data + GaoHR 全国大学基本信息","sourceUrl":"https://github.com/DaoSword/China-Education-Data","sourceDate":"2026-04-21","confidence":"medium","notes":"已补 GaoHR 2021 校级坐标；当前为学校级校址占位；需要后续 deep research 继续补本科生具体校区、是否大一分校和地铁距离。"}],"4136013437":[{"campusName":"湾里校区","campusAddress":"江西省南昌湾里梅岭大道1689号","province":"江西","city":"南昌","district":"","undergraduateScope":"unknown","freshmanOnly":"unknown","nearestMetroStation":"","sourceTitle":"DaoSword China-Education-Data","sourceUrl":"https://github.com/DaoSword/China-Education-Data","sourceDate":"2026-04-21","confidence":"low","notes":"此校区由 DaoSword 宽表中的标注校址补入；未在 geocoder 主结果中出现，建议后续以学校校区介绍页复核。"},{"campusName":"小蓝校区","campusAddress":"江西省南昌市小蓝经济开发区汇仁大道689号","province":"江西","city":"南昌","district":"小蓝经济开发区","undergraduateScope":"unknown","freshmanOnly":"unknown","nearestMetroStation":"","sourceTitle":"DaoSword China-Education-Data","sourceUrl":"https://github.com/DaoSword/China-Education-Data","sourceDate":"2026-04-21","confidence":"low","notes":"此校区由 DaoSword 宽表中的标注校址补入；未在 geocoder 主结果中出现，建议后续以学校校区介绍页复核。"}],"4136013438":[{"campusName":"主校区","campusAddress":"江西省共青城市青年大道78号","province":"江西","city":"南昌","district":"","lat":28.675444,"lng":115.923853,"undergraduateScope":"unknown","freshmanOnly":"unknown","nearestMetroStation":"","sourceTitle":"Naptie cn-university-geocoder + DaoSword China-Education-Data","sourceUrl":"https://github.com/Naptie/cn-university-geocoder","sourceDate":"2026-04-21","confidence":"medium","notes":"辅源：https://github.com/jtchen2k/hcu、https://daxue.cgsop.com/ 可用于后续人工校验校区沿革与本科去向。"}],"4136013439":[{"campusName":"主校区","campusAddress":"江西省赣州市章贡区红旗大道61号","province":"江西","city":"赣州","district":"赣州市章贡区","lat":25.852445,"lng":114.926706,"undergraduateScope":"unknown","freshmanOnly":"unknown","nearestMetroStation":"","sourceTitle":"Naptie cn-university-geocoder + DaoSword China-Education-Data","sourceUrl":"https://github.com/Naptie/cn-university-geocoder","sourceDate":"2026-04-21","confidence":"medium","notes":"辅源：https://github.com/jtchen2k/hcu、https://daxue.cgsop.com/ 可用于后续人工校验校区沿革与本科去向。"}],"4136013440":[{"campusName":"主校区","campusAddress":"江西省南昌市红谷滩新区明月山大道1599号","province":"江西","city":"南昌","district":"南昌市红谷滩新区","lat":28.547086,"lng":115.916444,"undergraduateScope":"unknown","freshmanOnly":"unknown","nearestMetroStation":"","sourceTitle":"Naptie cn-university-geocoder + DaoSword China-Education-Data","sourceUrl":"https://github.com/Naptie/cn-university-geocoder","sourceDate":"2026-04-21","confidence":"medium","notes":"辅源：https://github.com/jtchen2k/hcu、https://daxue.cgsop.com/ 可用于后续人工校验校区沿革与本科去向。"}],"4136013441":[{"campusName":"主校区","campusAddress":"江西省共青城市青年大道59号","province":"江西","city":"南昌","district":"","lat":28.747537,"lng":115.862173,"undergraduateScope":"unknown","freshmanOnly":"unknown","nearestMetroStation":"","sourceTitle":"Naptie cn-university-geocoder + DaoSword China-Education-Data","sourceUrl":"https://github.com/Naptie/cn-university-geocoder","sourceDate":"2026-04-21","confidence":"medium","notes":"辅源：https://github.com/jtchen2k/hcu、https://daxue.cgsop.com/ 可用于后续人工校验校区沿革与本科去向。"}],"4136013774":[{"campusName":"主校区","campusAddress":"江西省南昌市兴湾大道1999号","province":"江西","city":"南昌","district":"","lat":28.68192,"lng":115.946659,"undergraduateScope":"unknown","freshmanOnly":"unknown","nearestMetroStation":"","sourceTitle":"Naptie cn-university-geocoder + DaoSword China-Education-Data","sourceUrl":"https://github.com/Naptie/cn-university-geocoder","sourceDate":"2026-04-21","confidence":"medium","notes":"辅源：https://github.com/jtchen2k/hcu、https://daxue.cgsop.com/ 可用于后续人工校验校区沿革与本科去向。"}],"4136013775":[{"campusName":"老校区","campusAddress":"江西省抚州市赣东大道1111号","province":"江西","city":"抚州","district":"","undergraduateScope":"unknown","freshmanOnly":"unknown","nearestMetroStation":"","sourceTitle":"DaoSword China-Education-Data","sourceUrl":"https://github.com/DaoSword/China-Education-Data","sourceDate":"2026-04-21","confidence":"low","notes":"当前仅有聚合校址，尚未接入官方招生章程或校区说明页，暂不参与硬筛选推导。"},{"campusName":"新校区","campusAddress":"江西省抚州市文昌大道2766号","province":"江西","city":"抚州","district":"","undergraduateScope":"unknown","freshmanOnly":"unknown","nearestMetroStation":"","sourceTitle":"DaoSword China-Education-Data","sourceUrl":"https://github.com/DaoSword/China-Education-Data","sourceDate":"2026-04-21","confidence":"low","notes":"当前仅有聚合校址，尚未接入官方招生章程或校区说明页，暂不参与硬筛选推导。"}],"4136013776":[{"campusName":"主校区","campusAddress":"江西省南昌市湾里区先锋创客小镇","province":"江西","city":"南昌","district":"湾里区","lat":28.89911,"lng":115.811265,"undergraduateScope":"unknown","freshmanOnly":"unknown","nearestMetroStation":"","sourceTitle":"Naptie cn-university-geocoder + DaoSword China-Education-Data + ZsTs119/pg7go Baidu POI 数据集","sourceUrl":"https://github.com/Naptie/cn-university-geocoder","sourceDate":"2026-04-21","confidence":"high","notes":"百度 POI 精确匹配，坐标偏差约 1.17 km。"}],"4136013866":[{"campusName":"主校区","campusAddress":"南昌市红角洲卧龙路269号","province":"江西","city":"南昌","district":"","undergraduateScope":"unknown","freshmanOnly":"unknown","nearestMetroStation":"","sourceTitle":"DaoSword China-Education-Data","sourceUrl":"https://github.com/DaoSword/China-Education-Data","sourceDate":"2026-04-21","confidence":"low","notes":"当前为学校级校址占位；需要后续 deep research 继续补本科生具体校区、是否大一分校和地铁距离。"}],"4136013867":[{"campusName":"主校区","campusAddress":"江西省南昌市紫阳大道318号","province":"江西","city":"南昌","district":"","lat":28.652344,"lng":115.933827,"undergraduateScope":"unknown","freshmanOnly":"unknown","nearestMetroStation":"","sourceTitle":"Naptie cn-university-geocoder + DaoSword China-Education-Data","sourceUrl":"https://github.com/Naptie/cn-university-geocoder","sourceDate":"2026-04-21","confidence":"medium","notes":"辅源：https://github.com/jtchen2k/hcu、https://daxue.cgsop.com/ 可用于后续人工校验校区沿革与本科去向。"}],"4136013868":[{"campusName":"主校区","campusAddress":"江西省南昌市西湖区安石路69号","province":"江西","city":"南昌","district":"南昌市西湖区","lat":28.652961,"lng":115.892937,"undergraduateScope":"unknown","freshmanOnly":"unknown","nearestMetroStation":"","sourceTitle":"Naptie cn-university-geocoder + DaoSword China-Education-Data","sourceUrl":"https://github.com/Naptie/cn-university-geocoder","sourceDate":"2026-04-21","confidence":"medium","notes":"辅源：https://github.com/jtchen2k/hcu、https://daxue.cgsop.com/ 可用于后续人工校验校区沿革与本科去向。"}],"4136013869":[{"campusName":"主校区","campusAddress":"江西省南昌市经济技术开发区志敏大道1458号","province":"江西","city":"南昌","district":"经济技术开发区","lat":28.747969,"lng":115.855807,"undergraduateScope":"unknown","freshmanOnly":"unknown","nearestMetroStation":"","sourceTitle":"Naptie cn-university-geocoder + DaoSword China-Education-Data","sourceUrl":"https://github.com/Naptie/cn-university-geocoder","sourceDate":"2026-04-21","confidence":"medium","notes":"辅源：https://github.com/jtchen2k/hcu、https://daxue.cgsop.com/ 可用于后续人工校验校区沿革与本科去向。"}],"4136013870":[{"campusName":"主校区","campusAddress":"江西省上饶市旭日北大道358号","province":"江西","city":"上饶","district":"","lat":29.288905,"lng":117.855085,"undergraduateScope":"unknown","freshmanOnly":"unknown","nearestMetroStation":"","sourceTitle":"Naptie cn-university-geocoder + DaoSword China-Education-Data","sourceUrl":"https://github.com/Naptie/cn-university-geocoder","sourceDate":"2026-04-21","confidence":"medium","notes":"辅源：https://github.com/jtchen2k/hcu、https://daxue.cgsop.com/ 可用于后续人工校验校区沿革与本科去向。"}],"4136013871":[{"campusName":"东校区","campusAddress":"江西省南昌市青云谱区新溪桥东一路219号","province":"江西","city":"南昌","district":"青云谱区","lat":28.639698,"lng":115.923993,"undergraduateScope":"unknown","freshmanOnly":"unknown","nearestMetroStation":"","sourceTitle":"Naptie cn-university-geocoder + DaoSword China-Education-Data + ZsTs119/pg7go Baidu POI 数据集","sourceUrl":"https://github.com/Naptie/cn-university-geocoder","sourceDate":"2026-04-21","confidence":"high","notes":"校区地址与 DaoSword 宽表中的标注校区名一致。 百度 POI 近似匹配，坐标偏差约 0.99 km。"},{"campusName":"西校区","campusAddress":"江西省南昌市青云谱区新溪桥南一路41号","province":"江西","city":"南昌","district":"青云谱区","lat":28.631749,"lng":115.918303,"undergraduateScope":"unknown","freshmanOnly":"unknown","nearestMetroStation":"","sourceTitle":"Naptie cn-university-geocoder + DaoSword China-Education-Data + ZsTs119/pg7go Baidu POI 数据集","sourceUrl":"https://github.com/Naptie/cn-university-geocoder","sourceDate":"2026-04-21","confidence":"high","notes":"校区地址与 DaoSword 宽表中的标注校区名一致。 百度 POI 近似匹配，坐标偏差约 2.02 km。"}],"4136013872":[{"campusName":"主校区","campusAddress":"江西省樟树市四特大道266号","province":"江西","city":"宜春","district":"樟树市","lat":28.050722,"lng":115.551437,"undergraduateScope":"unknown","freshmanOnly":"unknown","nearestMetroStation":"","sourceTitle":"Naptie cn-university-geocoder + DaoSword China-Education-Data + ZsTs119/pg7go Baidu POI 数据集","sourceUrl":"https://github.com/Naptie/cn-university-geocoder","sourceDate":"2026-04-21","confidence":"high","notes":"百度 POI 精确匹配，坐标偏差约 1.16 km。"}],"4136013873":[{"campusName":"主校区","campusAddress":"江西省新余市渝水区赣西大道598号（劳动北路919号）新校区：江西省新余市仙女湖大道3039号","province":"江西","city":"新余","district":"新余市渝水区","lat":27.835437,"lng":114.927105,"undergraduateScope":"unknown","freshmanOnly":"unknown","nearestMetroStation":"","sourceTitle":"Naptie cn-university-geocoder + DaoSword China-Education-Data","sourceUrl":"https://github.com/Naptie/cn-university-geocoder","sourceDate":"2026-04-21","confidence":"high","notes":"校区地址与 DaoSword 宽表中的标注校区名一致。"}],"4136013965":[{"campusName":"主校区","campusAddress":"江西省南昌市小蓝经济开发区汇仁大道689号","province":"江西","city":"南昌","district":"南昌县","lat":28.579613,"lng":115.886096,"undergraduateScope":"unknown","freshmanOnly":"unknown","nearestMetroStation":"","sourceTitle":"Naptie cn-university-geocoder + DaoSword China-Education-Data + ZsTs119/pg7go Baidu POI 数据集","sourceUrl":"https://github.com/Naptie/cn-university-geocoder","sourceDate":"2026-04-21","confidence":"high","notes":"百度 POI 精确匹配，坐标偏差约 1.24 km。"}],"4136014166":[{"campusName":"主校区","campusAddress":"江西省新余市高新技术产业园区渝东大道818号","province":"江西","city":"新余","district":"渝水区","lat":27.835419,"lng":115.013899,"undergraduateScope":"unknown","freshmanOnly":"unknown","nearestMetroStation":"","sourceTitle":"Naptie cn-university-geocoder + DaoSword China-Education-Data + ZsTs119/pg7go Baidu POI 数据集","sourceUrl":"https://github.com/Naptie/cn-university-geocoder","sourceDate":"2026-04-21","confidence":"high","notes":"百度 POI 精确匹配，坐标偏差约 1.18 km。"}],"4136014167":[{"campusName":"主校区","campusAddress":"江西省九江市云山经济技术开发区","province":"江西","city":"九江","district":"永修县","lat":29.13505,"lng":115.723785,"undergraduateScope":"unknown","freshmanOnly":"unknown","nearestMetroStation":"","sourceTitle":"Naptie cn-university-geocoder + DaoSword China-Education-Data + ZsTs119/pg7go Baidu POI 数据集","sourceUrl":"https://github.com/Naptie/cn-university-geocoder","sourceDate":"2026-04-21","confidence":"high","notes":"百度 POI 精确匹配，坐标偏差约 1.18 km。"}],"4136014168":[{"campusName":"主校区","campusAddress":"江西省南昌市小蓝经开区汇仁大道1333号","province":"江西","city":"南昌","district":"南昌市小蓝经开区","lat":28.576593,"lng":115.871891,"undergraduateScope":"unknown","freshmanOnly":"unknown","nearestMetroStation":"","sourceTitle":"Naptie cn-university-geocoder + DaoSword China-Education-Data","sourceUrl":"https://github.com/Naptie/cn-university-geocoder","sourceDate":"2026-04-21","confidence":"medium","notes":"辅源：https://github.com/jtchen2k/hcu、https://daxue.cgsop.com/ 可用于后续人工校验校区沿革与本科去向。"}],"4136014241":[{"campusName":"主校区","campusAddress":"江西省新余市仙女湖名胜区","province":"江西","city":"新余","district":"渝水区","lat":27.800116,"lng":114.922027,"undergraduateScope":"unknown","freshmanOnly":"unknown","nearestMetroStation":"","sourceTitle":"Naptie cn-university-geocoder + DaoSword China-Education-Data + ZsTs119/pg7go Baidu POI 数据集","sourceUrl":"https://github.com/Naptie/cn-university-geocoder","sourceDate":"2026-04-21","confidence":"high","notes":"百度 POI 精确匹配，坐标偏差约 5.72 km。"}],"4136014249":[{"campusName":"主校区","campusAddress":"","province":"江西","city":"南昌","district":"","lat":28.766799,"lng":115.818002,"undergraduateScope":"unknown","freshmanOnly":"unknown","nearestMetroStation":"","sourceTitle":"Naptie cn-university-geocoder","sourceUrl":"https://github.com/Naptie/cn-university-geocoder","sourceDate":"2026-04-21","confidence":"low","notes":"暂仅保留单校址占位，后续需补官方校区页。"}],"4136014250":[{"campusName":"主校区","campusAddress":"江西省南昌市蒋巷西大道266号","province":"江西","city":"南昌","district":"","lat":28.749735,"lng":115.952294,"undergraduateScope":"unknown","freshmanOnly":"unknown","nearestMetroStation":"","sourceTitle":"Naptie cn-university-geocoder + DaoSword China-Education-Data","sourceUrl":"https://github.com/Naptie/cn-university-geocoder","sourceDate":"2026-04-21","confidence":"medium","notes":"辅源：https://github.com/jtchen2k/hcu、https://daxue.cgsop.com/ 可用于后续人工校验校区沿革与本科去向。"}],"4136014321":[{"campusName":"主校区","campusAddress":"江西省南昌市南昌县向塘镇丽湖中大道99号","province":"江西","city":"南昌","district":"南昌市南昌县","lat":28.450118,"lng":115.94761,"undergraduateScope":"unknown","freshmanOnly":"unknown","nearestMetroStation":"","sourceTitle":"Naptie cn-university-geocoder + DaoSword China-Education-Data","sourceUrl":"https://github.com/Naptie/cn-university-geocoder","sourceDate":"2026-04-21","confidence":"medium","notes":"辅源：https://github.com/jtchen2k/hcu、https://daxue.cgsop.com/ 可用于后续人工校验校区沿革与本科去向。"}],"4136014402":[{"campusName":"主校区","campusAddress":"江西省景德镇市浮梁县县衙路119号","province":"江西","city":"景德镇","district":"浮梁县","lat":29.362531,"lng":117.228345,"undergraduateScope":"unknown","freshmanOnly":"unknown","nearestMetroStation":"","sourceTitle":"Naptie cn-university-geocoder + DaoSword China-Education-Data + ZsTs119/pg7go Baidu POI 数据集","sourceUrl":"https://github.com/Naptie/cn-university-geocoder","sourceDate":"2026-04-21","confidence":"high","notes":"百度 POI 精确匹配，坐标偏差约 1.20 km。"}],"4136014403":[{"campusName":"主校区","campusAddress":"江西省共青城市共青大道1号","province":"江西","city":"九江","district":"","undergraduateScope":"unknown","freshmanOnly":"unknown","nearestMetroStation":"","sourceTitle":"DaoSword China-Education-Data","sourceUrl":"https://github.com/DaoSword/China-Education-Data","sourceDate":"2026-04-21","confidence":"low","notes":"当前为学校级校址占位；需要后续 deep research 继续补本科生具体校区、是否大一分校和地铁距离。"}],"4136014437":[{"campusName":"主校区","campusAddress":"江西省南昌市经济开发区瑞香路889号","province":"江西","city":"南昌","district":"南昌市经济开发区","lat":28.547086,"lng":115.916444,"undergraduateScope":"unknown","freshmanOnly":"unknown","nearestMetroStation":"","sourceTitle":"Naptie cn-university-geocoder + DaoSword China-Education-Data","sourceUrl":"https://github.com/Naptie/cn-university-geocoder","sourceDate":"2026-04-21","confidence":"medium","notes":"辅源：https://github.com/jtchen2k/hcu、https://daxue.cgsop.com/ 可用于后续人工校验校区沿革与本科去向。"}],"4136014465":[{"campusName":"主校区","campusAddress":"江西省赣州市蓉江新区高校园区35号","province":"江西","city":"赣州","district":"章贡区","lat":25.797057,"lng":114.891909,"undergraduateScope":"unknown","freshmanOnly":"unknown","nearestMetroStation":"","sourceTitle":"Naptie cn-university-geocoder + DaoSword China-Education-Data + ZsTs119/pg7go Baidu POI 数据集","sourceUrl":"https://github.com/Naptie/cn-university-geocoder","sourceDate":"2026-04-21","confidence":"high","notes":"百度 POI 精确匹配，坐标偏差约 1.05 km。"}],"4136014476":[{"campusName":"主校区","campusAddress":"江西省南昌市经济技术开发区北山路99号","province":"江西","city":"南昌","district":"经济技术开发区","lat":28.754604,"lng":115.870474,"undergraduateScope":"unknown","freshmanOnly":"unknown","nearestMetroStation":"","sourceTitle":"Naptie cn-university-geocoder + DaoSword China-Education-Data","sourceUrl":"https://github.com/Naptie/cn-university-geocoder","sourceDate":"2026-04-21","confidence":"medium","notes":"辅源：https://github.com/jtchen2k/hcu、https://daxue.cgsop.com/ 可用于后续人工校验校区沿革与本科去向。"}],"4136014494":[{"campusName":"主校区","campusAddress":"江西省宜春市袁州区锦绣大道1699号","province":"江西","city":"宜春","district":"宜春市袁州区","lat":27.815029,"lng":114.333586,"undergraduateScope":"unknown","freshmanOnly":"unknown","nearestMetroStation":"","sourceTitle":"Naptie cn-university-geocoder + DaoSword China-Education-Data","sourceUrl":"https://github.com/Naptie/cn-university-geocoder","sourceDate":"2026-04-21","confidence":"medium","notes":"辅源：https://github.com/jtchen2k/hcu、https://daxue.cgsop.com/ 可用于后续人工校验校区沿革与本科去向。"}],"4136014504":[{"campusName":"主校区","campusAddress":"江西省吉安市中心城区吉安南大道133号","province":"江西","city":"吉安","district":"吉州区","lat":27.042836,"lng":114.903217,"undergraduateScope":"unknown","freshmanOnly":"unknown","nearestMetroStation":"","sourceTitle":"Naptie cn-university-geocoder + DaoSword China-Education-Data + ZsTs119/pg7go Baidu POI 数据集","sourceUrl":"https://github.com/Naptie/cn-university-geocoder","sourceDate":"2026-04-21","confidence":"high","notes":"百度 POI 精确匹配，坐标偏差约 6.90 km。"}],"4136014505":[{"campusName":"主校区","campusAddress":"江西省丰城市龙津湖总部经济基地大学城","province":"江西","city":"宜春","district":"丰城市","lat":28.24383,"lng":115.766463,"undergraduateScope":"unknown","freshmanOnly":"unknown","nearestMetroStation":"","sourceTitle":"Naptie cn-university-geocoder + DaoSword China-Education-Data + ZsTs119/pg7go Baidu POI 数据集","sourceUrl":"https://github.com/Naptie/cn-university-geocoder","sourceDate":"2026-04-21","confidence":"high","notes":"百度 POI 精确匹配，坐标偏差约 1.17 km。"}],"4136014537":[{"campusName":"主校区","campusAddress":"江西省鹰潭市信江新区滨江东大道1号","province":"江西","city":"鹰潭","district":"贵溪市","lat":28.304236,"lng":117.053861,"undergraduateScope":"unknown","freshmanOnly":"unknown","nearestMetroStation":"","sourceTitle":"Naptie cn-university-geocoder + DaoSword China-Education-Data + ZsTs119/pg7go Baidu POI 数据集","sourceUrl":"https://github.com/Naptie/cn-university-geocoder","sourceDate":"2026-04-21","confidence":"high","notes":"百度 POI 精确匹配，坐标偏差约 1.12 km。"}],"4136014544":[{"campusName":"主校区","campusAddress":"江西省南昌市蒋巷大道266号","province":"江西","city":"南昌","district":"","lat":28.747148,"lng":115.948739,"undergraduateScope":"unknown","freshmanOnly":"unknown","nearestMetroStation":"","sourceTitle":"Naptie cn-university-geocoder + DaoSword China-Education-Data","sourceUrl":"https://github.com/Naptie/cn-university-geocoder","sourceDate":"2026-04-21","confidence":"medium","notes":"辅源：https://github.com/jtchen2k/hcu、https://daxue.cgsop.com/ 可用于后续人工校验校区沿革与本科去向。"}],"4136014569":[{"campusName":"主校区","campusAddress":"江西省赣州市蓉江新区高校园区","province":"江西","city":"赣州","district":"章贡区","lat":25.774739,"lng":114.889135,"undergraduateScope":"unknown","freshmanOnly":"unknown","nearestMetroStation":"","sourceTitle":"Naptie cn-university-geocoder + DaoSword China-Education-Data + ZsTs119/pg7go Baidu POI 数据集","sourceUrl":"https://github.com/Naptie/cn-university-geocoder","sourceDate":"2026-04-21","confidence":"high","notes":"百度 POI 精确匹配，坐标偏差约 1.16 km。"}],"4136014656":[{"campusName":"主校区","campusAddress":"江西省萍乡市安源区武功山中大道333号","province":"江西","city":"萍乡","district":"安源区","lat":27.654945,"lng":113.919707,"undergraduateScope":"unknown","freshmanOnly":"unknown","nearestMetroStation":"","sourceTitle":"Naptie cn-university-geocoder + DaoSword China-Education-Data + ZsTs119/pg7go Baidu POI 数据集","sourceUrl":"https://github.com/Naptie/cn-university-geocoder","sourceDate":"2026-04-21","confidence":"high","notes":"百度 POI 精确匹配，坐标偏差约 1.19 km。"}],"4136014657":[{"campusName":"主校区","campusAddress":"江西省上饶市婺源县思口路88号","province":"江西","city":"上饶","district":"上饶市婺源县","lat":29.271985,"lng":117.835858,"undergraduateScope":"unknown","freshmanOnly":"unknown","nearestMetroStation":"","sourceTitle":"Naptie cn-university-geocoder + DaoSword China-Education-Data","sourceUrl":"https://github.com/Naptie/cn-university-geocoder","sourceDate":"2026-04-21","confidence":"medium","notes":"辅源：https://github.com/jtchen2k/hcu、https://daxue.cgsop.com/ 可用于后续人工校验校区沿革与本科去向。"}],"4136014665":[{"campusName":"主校区","campusAddress":"江西省赣州市经济技术开发区赣州新能源汽车科技城内","province":"江西","city":"赣州","district":"市经济技术开发区","lat":25.797322,"lng":114.767717,"undergraduateScope":"unknown","freshmanOnly":"unknown","nearestMetroStation":"","sourceTitle":"Naptie cn-university-geocoder + DaoSword China-Education-Data","sourceUrl":"https://github.com/Naptie/cn-university-geocoder","sourceDate":"2026-04-21","confidence":"medium","notes":"辅源：https://github.com/jtchen2k/hcu、https://daxue.cgsop.com/ 可用于后续人工校验校区沿革与本科去向。"}],"4136014705":[{"campusName":"主校区","campusAddress":"江西省南昌市湾里区翠岩路466号","province":"江西","city":"南昌","district":"南昌市湾里区","lat":28.675168,"lng":115.998369,"undergraduateScope":"unknown","freshmanOnly":"unknown","nearestMetroStation":"","sourceTitle":"Naptie cn-university-geocoder + DaoSword China-Education-Data","sourceUrl":"https://github.com/Naptie/cn-university-geocoder","sourceDate":"2026-04-21","confidence":"medium","notes":"辅源：https://github.com/jtchen2k/hcu、https://daxue.cgsop.com/ 可用于后续人工校验校区沿革与本科去向。"}],"4136014706":[{"campusName":"主校区","campusAddress":"江西省九江市国家级出口加工区汇源路8号","province":"江西","city":"九江","district":"国家级出口加工区","lat":29.607216,"lng":115.916805,"undergraduateScope":"unknown","freshmanOnly":"unknown","nearestMetroStation":"","sourceTitle":"Naptie cn-university-geocoder + DaoSword China-Education-Data","sourceUrl":"https://github.com/Naptie/cn-university-geocoder","sourceDate":"2026-04-21","confidence":"medium","notes":"辅源：https://github.com/jtchen2k/hcu、https://daxue.cgsop.com/ 可用于后续人工校验校区沿革与本科去向。"}],"4136014748":[{"campusName":"主校区","campusAddress":"江西省赣州市会昌县白鹅乡和君小镇","province":"江西","city":"赣州","district":"赣州市会昌县","undergraduateScope":"unknown","freshmanOnly":"unknown","nearestMetroStation":"","sourceTitle":"DaoSword China-Education-Data","sourceUrl":"https://github.com/DaoSword/China-Education-Data","sourceDate":"2026-04-21","confidence":"low","notes":"当前为学校级校址占位；需要后续 deep research 继续补本科生具体校区、是否大一分校和地铁距离。"}]}